{"de":{"audio":"https://upload.wikimedia.org/wikipedia/commons/d/d4/De-dies.ogg","basic form":"dies","entries":[{"header":{"de":"Pronomen, Demonstrativpronomen","en":"pronoun, demonstrative pronoun"},"subentries":[{"header":{"de":"Nicht mehr gültige Schreibweisen","en":"No longer valid spellings"},"subentry":"\u003cdl\u003e\u003cdd\u003edieß\u003c/dd\u003e\u003c/dl\u003e"},{"header":{"de":"Worttrennung","en":"hyphenation"},"subentry":"\u003cdl\u003e\u003cdd\u003edies, die·ser, die·se, die·ses\u003c/dd\u003e\u003c/dl\u003e"},{"header":{"de":"Aussprache","en":"pronunciation"},"subentry":"\u003cdl\u003e\u003cdd\u003eIPA: [diːs]\u003c/dd\u003e\u003cdd\u003eHörbeispiele: \u003cspan class=audio-available audio=https://upload.wikimedia.org/wikipedia/commons/d/d4/De-dies.ogg\u003edies\u003c/span\u003e\u003c/dd\u003e\u003c/dl\u003e"},{"header":{"de":"Bedeutungen","en":"meanings"},"subentry":"\u003cdl\u003e\u003cdd\u003e[1] adverbialer Gebrauch, um ein ganz bestimmtes, nahe liegendes Nomen hervorzuheben\u003c/dd\u003e\u003c/dl\u003e"},{"header":{"de":"Herkunft","en":"origin"},"subentry":"\u003cdl\u003e\u003cdd\u003eAus germanisch. Siehe auch engl. this. \u003c/dd\u003e\u003c/dl\u003e"},{"header":{"de":"Gegenwörter","en":"antonyms"},"subentry":"\u003cdl\u003e\u003cdd\u003e[1] das, jene\u003c/dd\u003e\u003c/dl\u003e"},{"header":{"de":"Beispiele","en":"examples"},"subentry":"\u003cdl\u003e\u003cdd\u003e[1] \u003ci\u003eDies\u003c/i\u003e ist mein Bruder.\u003c/dd\u003e\u003cdd\u003e[1] Ich möchte aber \u003ci\u003ediesen\u003c/i\u003e haben.\u003c/dd\u003e\u003c/dl\u003e"},{"header":{"de":"Redewendungen","en":"idioms"},"subentry":"\u003cdl\u003e\u003cdd\u003edies und das, dieses und jenes\u003c/dd\u003e\u003c/dl\u003e"},{"header":{"de":"Übersetzungen","en":"translations"},"subentry":"\u0026#160;\u003ctable class=transtable\u003e\u003ctbody\u003e\u003ctr\u003e\u003ctd\u003e\u003cul\u003e\u003cli\u003eArabisch\u0026#160;\u003csmall\u003e(DMG)\u003c/small\u003e\u003cul\u003e\u003cli\u003emodernes Hocharabisch: [1] ه\u0026#1648;ذَا (hāḏā)\u003c/li\u003e\u003c/ul\u003e\u003c/li\u003e\u003cli\u003eEnglisch: [1] this\u0026#160;\u003c/li\u003e\u003cli\u003eEsperanto: [1] ĉi tio, tio ĉi, ĉi tiu, tiu ĉi\u0026#160;\u003c/li\u003e\u003cli\u003eFinnisch: [1] tämä\u0026#160;\u003c/li\u003e\u003cli\u003eFranzösisch: [1] ceci\u0026#160;\u003c/li\u003e\u003cli\u003eIdo: [1] ca\u0026#160;\u003c/li\u003e\u003c/ul\u003e\u003c/td\u003e\u003ctd\u003e\u003c/td\u003e\u003ctd\u003e\u003cul\u003e\u003cli\u003eInterlingua: [1] isto\u0026#160;\u003cem title=\"Genus: Neutrum (grammatikal. Geschlecht: sächlich)\"\u003en\u003c/em\u003e\u003c/li\u003e\u003cli\u003eItalienisch: [1] questo\u0026#160;\u003c/li\u003e\u003cli\u003eNiederländisch: [1] deze, dit\u0026#160;\u003c/li\u003e\u003cli\u003eRussisch: [1] это\u0026#160;()\u0026#160;\u003c/li\u003e\u003cli\u003eSchwedisch: [1] den här, det här, de här\u0026#160;\u003c/li\u003e\u003cli\u003eSpanisch: [1] esto\u0026#160;\u003cem title=\"Genus: Neutrum (grammatikal. Geschlecht: sächlich)\"\u003en\u003c/em\u003e, este\u0026#160;\u003cem title=\"Genus: Maskulinum (grammatikalisches Geschlecht: männlich)\"\u003em\u003c/em\u003e, esta\u0026#160;\u003cem title=\"Genus: Femininum (grammatikal. Geschlecht: weiblich)\"\u003ef\u003c/em\u003e\u003c/li\u003e\u003c/ul\u003e\u003c/td\u003e\u003c/tr\u003e\u003c/tbody\u003e\u003c/table\u003e"}],"tables":[{"Akkusativ Plural":"diese","Akkusativ Singular f":"diese","Akkusativ Singular m":"diesen","Akkusativ Singular n":"dieses","Akkusativ Singular n*":"dies","Dativ Plural":"diesen","Dativ Singular f":"dieser","Dativ Singular m":"diesem","Dativ Singular n":"diesem","Genitiv Plural":"dieser","Genitiv Singular f":"dieser","Genitiv Singular m":"dieses","Genitiv Singular n":"dieses","Nominativ Plural":"diese","Nominativ Singular f":"diese","Nominativ Singular m":"dieser","Nominativ Singular n":"dieses","Nominativ Singular n*":"dies","html":"\u003ctable class=wikitable\u003e\u003ctbody\u003e\u003ctr\u003e\u003cth rowspan=2\u003e\u003c/th\u003e\u003cth colspan=3\u003e\u003cspan lang=de\u003eSingular\u003c/span\u003e\u003cbr\u003e\u003cspan lang=en class=trans\u003esingular\u003c/span\u003e\u003c/th\u003e\u003cth\u003e\u003cspan lang=de\u003ePlural\u003c/span\u003e\u003cbr\u003e\u003cspan lang=en class=trans\u003eplural\u003c/span\u003e\u003c/th\u003e\u003c/tr\u003e\u003ctr\u003e\u003cth\u003e\u003cspan lang=de\u003eMaskulinum\u003c/span\u003e\u003cbr\u003e\u003cspan lang=en class=trans\u003emasculine\u003c/span\u003e\u003c/th\u003e\u003cth\u003e\u003cspan lang=de\u003eFemininum\u003c/span\u003e\u003cbr\u003e\u003cspan lang=en class=trans\u003efeminine\u003c/span\u003e\u003c/th\u003e\u003cth\u003e\u003cspan lang=de\u003eNeutrum\u003c/span\u003e\u003cbr\u003e\u003cspan lang=en class=trans\u003eneuter\u003c/span\u003e\u003c/th\u003e\u003cth\u003e—\u003c/th\u003e\u003c/tr\u003e\u003ctr\u003e\u003cth style=text-align:left\u003e\u003cspan lang=de\u003eNominativ\u003c/span\u003e\u003cbr\u003e\u003cspan lang=en class=trans\u003enominative\u003c/span\u003e\u003c/th\u003e\u003ctd\u003edieser\u003c/td\u003e\u003ctd\u003ediese\u003c/td\u003e\u003ctd\u003edieses\u003cbr\u003edies\u003c/td\u003e\u003ctd\u003ediese\u003c/td\u003e\u003c/tr\u003e\u003ctr\u003e\u003cth style=text-align:left\u003e\u003cspan lang=de\u003eGenitiv\u003c/span\u003e\u003cbr\u003e\u003cspan lang=en class=trans\u003egenitive\u003c/span\u003e\u003c/th\u003e\u003ctd\u003edieses\u003c/td\u003e\u003ctd\u003edieser\u003c/td\u003e\u003ctd\u003edieses\u003c/td\u003e\u003ctd\u003edieser\u003c/td\u003e\u003c/tr\u003e\u003ctr\u003e\u003cth style=text-align:left\u003e\u003cspan lang=de\u003eDativ\u003c/span\u003e\u003cbr\u003e\u003cspan lang=en class=trans\u003edative\u003c/span\u003e\u003c/th\u003e\u003ctd\u003ediesem\u003c/td\u003e\u003ctd\u003edieser\u003c/td\u003e\u003ctd\u003ediesem\u003c/td\u003e\u003ctd\u003ediesen\u003c/td\u003e\u003c/tr\u003e\u003ctr\u003e\u003cth style=text-align:left\u003e\u003cspan lang=de\u003eAkkusativ\u003c/span\u003e\u003cbr\u003e\u003cspan lang=en class=trans\u003eaccusative\u003c/span\u003e\u003c/th\u003e\u003ctd\u003ediesen\u003c/td\u003e\u003ctd\u003ediese\u003c/td\u003e\u003ctd\u003edieses\u003cbr\u003edies\u003c/td\u003e\u003ctd\u003ediese\u003c/td\u003e\u003c/tr\u003e\u003c/tbody\u003e\u003c/table\u003e"}]}],"title":"dies","translation":"this ","variants":["dies","dieser","diese","dieses","diesem","diesen"],"word classes":["Pronomen","Demonstrativpronomen"]},"id":"dies"}