{"de":{"audio":"https://upload.wikimedia.org/wikipedia/commons/6/6a/De-f%C3%BCr.ogg","basic form":"für","coda":[{"header":{"de":"Ähnliche Wörter","en":"similar words"},"subentry":"\u003cdl\u003e\u003cdd\u003e\u003ci\u003eähnlich geschrieben und/oder ausgesprochen:\u003c/i\u003e führ, Füür, Füer\u003c/dd\u003e\u003c/dl\u003e"}],"entries":[{"header":{"de":"Präposition","en":"preposition"},"subentries":[{"header":{"de":"Aussprache","en":"pronunciation"},"subentry":"\u003cdl\u003e\u003cdd\u003eIPA: [fyːɐ̯]\u003c/dd\u003e\u003cdd\u003eHörbeispiele: \u003cspan class=audio-available audio=https://upload.wikimedia.org/wikipedia/commons/6/6a/De-f%C3%BCr.ogg\u003efür\u003c/span\u003e\u003c/dd\u003e\u003c/dl\u003e"},{"header":{"de":"Bedeutungen","en":"meanings"},"subentry":"\u003cdl\u003e\u003cdd\u003e[1] \u003ci\u003emit Akkusativ:\u003c/i\u003e etwas oder jemand ist an etwas jemanden gerichtet, bestimmt, zugeordnet\u003c/dd\u003e\u003cdd\u003e[2] \u003ci\u003emit Akkusativ:\u003c/i\u003e bestimmt oder gibt einen Zweck, einen Nutzen, eine Absicht, ein Ziel an; bestimmt einen Vorteil oder Nachteil, einen Zuschlag, eine Bestimmung jemandes oder etwas\u003c/dd\u003e\u003cdd\u003e[3] \u003ci\u003emit Akkusativ:\u003c/i\u003e gegen, ein Mittel gegen\u003c/dd\u003e\u003cdd\u003e[4] \u003ci\u003emit Akkusativ:\u003c/i\u003e wegen, bestimmt oder gibt einen Grund, eine Ursache an\u003c/dd\u003e\u003cdd\u003e[5] \u003ci\u003emit Akkusativ:\u003c/i\u003e bestimmt oder gibt eine Wertung, Auffassung, Meinung wieder\u003c/dd\u003e\u003cdd\u003e[6] \u003ci\u003emit Akkusativ:\u003c/i\u003e bestimmt oder gibt eine Leistung, einen Wert, einen Preis an\u003c/dd\u003e\u003cdd\u003e[7] \u003ci\u003emit Akkusativ:\u003c/i\u003e anstelle, vertretend, vergleichend\u003c/dd\u003e\u003cdd\u003e[8] \u003ci\u003emit Akkusativ:\u003c/i\u003e bestimmt oder gibt einen Zeitraum oder Zeitpunkt an\u003c/dd\u003e\u003cdd\u003e[9] \u003ci\u003emit Akkusativ:\u003c/i\u003e bestimmt oder gibt eine Folge an\u003c/dd\u003e\u003c/dl\u003e"},{"header":{"de":"Abkürzungen","en":"abbreviations"},"subentry":"\u003cdl\u003e\u003cdd\u003e[1–9] f.\u003c/dd\u003e\u003c/dl\u003e"},{"header":{"de":"Herkunft","en":"origin"},"subentry":"\u003cdl\u003e\u003cdd\u003ealthochdeutsch \u003ci\u003efuri\u003c/i\u003e „vor“, „für“ \u003c/dd\u003e\u003c/dl\u003e"},{"header":{"de":"Sinnverwandte Wörter","en":"words with similar meanings"},"subentry":"\u003cdl\u003e\u003cdd\u003e\u003ci\u003ehistorisch:\u003c/i\u003e vor\u003c/dd\u003e\u003c/dl\u003e"},{"header":{"de":"Beispiele","en":"examples"},"subentry":"\u003cdl\u003e\u003cdd\u003e[1] Ich habe ein Geschenk \u003ci\u003efür\u003c/i\u003e dich.\u003c/dd\u003e\u003cdd\u003e[2] Wir treten \u003ci\u003efür\u003c/i\u003e die Menschenrechte ein.\u003c/dd\u003e\u003cdd\u003e[3] Verschreiben sie mir bitte etwas \u003ci\u003efür\u003c/i\u003e meine Halsschmerzen.\u003c/dd\u003e\u003cdd\u003e[4] \u003ci\u003eFür\u003c/i\u003e diese Frechheit wurden nicht du, sondern wir bestraft.\u003c/dd\u003e\u003cdd\u003e[5] Er hält das \u003ci\u003efür\u003c/i\u003e ungeeignet.\u003c/dd\u003e\u003cdd\u003e[6] \u003ci\u003eFür\u003c/i\u003e drei Euro in der Stunde arbeiten?\u003c/dd\u003e\u003cdd\u003e[7] Paul halten alle \u003ci\u003efür\u003c/i\u003e einen Besserwisser.\u003c/dd\u003e\u003cdd\u003e[8] \u003ci\u003eFür\u003c/i\u003e morgen elf Uhr habe ich das Taxi bestellt.\u003c/dd\u003e\u003cdd\u003e[8] Du sollst unsere Katze nur \u003ci\u003efür\u003c/i\u003e drei Wochen beaufsichtigen und füttern.\u003c/dd\u003e\u003cdd\u003e[9] Am besten wir gehen das Schritt \u003ci\u003efür\u003c/i\u003e Schritt noch einmal durch.\u003c/dd\u003e\u003c/dl\u003e"},{"header":{"de":"Redewendungen","en":"idioms"},"subentry":"\u003cdl\u003e\u003cdd\u003efür und für (veraltet), Mann für Mann, Schritt für Schritt, was für, was für ein\u003c/dd\u003e\u003c/dl\u003e"},{"header":{"de":"Charakteristische Wortkombinationen","en":"characteristic word combinations"},"subentry":"\u003cdl\u003e\u003cdd\u003efür nichts, für umsonst\u003c/dd\u003e\u003c/dl\u003e"},{"header":{"de":"Wortbildungen","en":"word formations"},"subentry":"\u003cdl\u003e\u003cdd\u003edafür, hierfür, wofür\u003c/dd\u003e\u003cdd\u003e\u003ci\u003eWortbildungen mit dem Präfix für Substantive und Verben „für-“ siehe dort\u003c/i\u003e\u003c/dd\u003e\u003c/dl\u003e"},{"header":{"de":"Übersetzungen","en":"translations"},"subentry":"\u0026#160;\u003ctable class=transtable\u003e\u003ctbody\u003e\u003ctr\u003e\u003ctd\u003e\u003cul\u003e\u003cli\u003eBulgarisch: [1] за\u0026#160;(za)\u0026#160;\u003c/li\u003e\u003cli\u003eEnglisch: [1] for\u0026#160;\u003c/li\u003e\u003cli\u003eEsperanto: [1] por\u0026#160;\u003c/li\u003e\u003cli\u003eFranzösisch: [1] pour\u0026#160;\u003c/li\u003e\u003cli\u003eInterlingua: [1] pro\u0026#160;\u003c/li\u003e\u003cli\u003eItalienisch: [1] per\u0026#160;\u003c/li\u003e\u003cli\u003eJapanisch: [1] 向け\u0026#160;(むけ, muke)\u0026#160;\u003c/li\u003e\u003cli\u003eKurdisch: [1] ji bo\u0026#160;(), bo\u0026#160;()\u0026#160;\u003c/li\u003e\u003cli\u003eNiederländisch: [1] voor\u0026#160;\u003c/li\u003e\u003cli\u003ePlautdietsch: [2] fa\u003c/li\u003e\u003c/ul\u003e\u003c/td\u003e\u003ctd\u003e\u003c/td\u003e\u003ctd\u003e\u003cul\u003e\u003cli\u003ePolnisch: [1] dla\u0026#160;\u003c/li\u003e\u003cli\u003ePortugiesisch: [1] para\u0026#160;\u003c/li\u003e\u003cli\u003eRussisch: [1] для\u0026#160;(dlja); [2] за\u0026#160;(za)\u0026#160;\u003c/li\u003e\u003cli\u003eSchwedisch: [1–9] för; [1] åt, till; [3] mot\u0026#160;\u003c/li\u003e\u003cli\u003eSlowakisch: [1,\u0026#160;2] pre; [3] proti; [4–7, 9] za; [8] na\u0026#160;\u003c/li\u003e\u003cli\u003eSpanisch: [1,\u0026#160;2] por, para\u0026#160;\u003c/li\u003e\u003cli\u003eTschechisch: [1,\u0026#160;2] pro; [3] proti; [4–7, 9] za; [8] na\u0026#160;\u003c/li\u003e\u003cli\u003eTürkisch: [1] için\u0026#160;\u003c/li\u003e\u003cli\u003eUkrainisch: [1] для\u0026#160;(), за\u0026#160;(), на\u0026#160;()\u0026#160;\u003c/li\u003e\u003c/ul\u003e\u003c/td\u003e\u003c/tr\u003e\u003c/tbody\u003e\u003c/table\u003e\u003ctable class=dialects\u003e\u003ctbody\u003e\u003ctr\u003e\u003cth colspan=5 style=background-color:#f5fafe;text-align:left\u003eDialektausdrücke:\u003c/th\u003e\u003c/tr\u003e\u003ctr\u003e\u003ctd\u003e\u003cul\u003e\u003cli\u003eNiedersächsisch: [1–9] för\u0026#160;\u003c/li\u003e\u003c/ul\u003e\u003c/td\u003e\u003ctd\u003e\u003c/td\u003e\u003ctd\u003e\u003cul\u003e\u003cli\u003eThüringisch: [1–9] for\u003c/li\u003e\u003c/ul\u003e\u003c/td\u003e\u003c/tr\u003e\u003c/tbody\u003e\u003c/table\u003e\u003ctable class=noprint\u003e\u003ctbody\u003e\u003ctr\u003e\u003ctd\u003ePrimäre Präpositionen (Deutsch)\u003cp\u003eab\u0026#160;\u0026#124; an\u0026#160;\u0026#124; auf\u0026#160;\u0026#124; aus\u0026#160;\u0026#124; bei\u0026#160;\u0026#124; bis\u0026#160;\u0026#124; durch\u0026#160;\u0026#124; für\u0026#160;\u0026#124; gegen\u0026#160;\u0026#124; hinter\u0026#160;\u0026#124; in\u0026#160;\u0026#124; mit\u0026#160;\u0026#124; nach\u0026#160;\u0026#124; neben\u0026#160;\u0026#124; ohne\u0026#160;\u0026#124; seit\u0026#160;\u0026#124; über\u0026#160;\u0026#124; um\u0026#160;\u0026#124; unter\u0026#160;\u0026#124; von\u0026#160;\u0026#124; vor\u0026#160;\u0026#124; wegen\u0026#160;\u0026#124; zu\u0026#160;\u0026#124; zwischen\u0026#160;\u0026#124; alle Präpositionen\u003c/p\u003e\u003c/td\u003e\u003c/tr\u003e\u003c/tbody\u003e\u003c/table\u003e"}]}],"title":"für","translation":"for ","variants":["für"],"word classes":["Präposition"]},"id":"für"}