{"de":{"audio":"https://upload.wikimedia.org/wikipedia/commons/8/84/De-hoch.ogg","basic form":"hoch","coda":[{"header":{"de":"Ähnliche Wörter","en":"similar words"},"subentry":"\u003cdl\u003e\u003cdd\u003e\u003ci\u003eähnlich geschrieben und/oder ausgesprochen:\u003c/i\u003e Loch\u003c/dd\u003e\u003c/dl\u003e"}],"entries":[{"header":{"de":"Adjektiv","en":"adjective"},"subentries":[{"header":{"de":"Worttrennung","en":"hyphenation"},"subentry":"\u003cdl\u003e\u003cdd\u003ehoch, Komparativ: hö·her, Superlativ: höchs·ten\u003c/dd\u003e\u003c/dl\u003e"},{"header":{"de":"Aussprache","en":"pronunciation"},"subentry":"\u003cdl\u003e\u003cdd\u003eIPA: [hoːx]\u003c/dd\u003e\u003cdd\u003eHörbeispiele: \u003cspan class=audio-available audio=https://upload.wikimedia.org/wikipedia/commons/8/84/De-hoch.ogg\u003ehoch\u003c/span\u003e, \u003cspan class=audio-available audio=https://upload.wikimedia.org/wikipedia/commons/2/23/De-at-hoch.ogg\u003ehoch\u0026#160;(Österreich)\u003c/span\u003e\u003c/dd\u003e\u003c/dl\u003e"},{"header":{"de":"Bedeutungen","en":"meanings"},"subentry":"\u003cdl\u003e\u003cdd\u003e[1] weit oben befindlich\u003c/dd\u003e\u003cdd\u003e[2] groß in der Ausdehnung nach oben; eine bestimmte Höhe aufweisend\u003c/dd\u003e\u003cdd\u003e[3] \u003ci\u003eakustische Wahrnehmung\u003c/i\u003e: mit großer Schwingungszahl\u003c/dd\u003e\u003cdd\u003e[4] \u003ci\u003esozial:\u003c/i\u003e vornehm, im Rang weit oben stehend\u003c/dd\u003e\u003cdd\u003e[5] \u003ci\u003eMathematik,\u003c/i\u003e hoch …\u0026#160;: zur …-ten Potenz erhoben\u003c/dd\u003e\u003cdd\u003e[6] der Menge nach weit oben liegend\u003c/dd\u003e\u003cdd\u003e[7] dem Wert nach weit oben liegend\u003c/dd\u003e\u003cdd\u003e[8] zeitlich fortgeschritten\u003c/dd\u003e\u003cdd\u003e[9] \u003ci\u003eim Sinne von:\u003c/i\u003e in Richtung nach oben\u003c/dd\u003e\u003cdd\u003e[10] \u003ci\u003eim Sinne von:\u003c/i\u003e nicht verstehen, zu schwierig\u003c/dd\u003e\u003cdd\u003e[11] \u003ci\u003eNamibia,\u0026#32;von Niederschlägen\u0026#58;\u003c/i\u003e von starkem Ausmaß, von großer Intensität\u003c/dd\u003e\u003c/dl\u003e"},{"header":{"de":"Herkunft","en":"origin"},"subentry":"\u003cdl\u003e\u003cdd\u003eGermanisch \u003ci\u003e*hauha-\u003c/i\u003e (Adjektiv) „hoch“, althochdeutsch \u003ci\u003ehōh, mittelhochdeutsch \u003c/i\u003ehōch\u003ci\u003e, belegt seit dem 8. Jahrhundert.\u003c/i\u003e\u003c/dd\u003e\u003cdd\u003eIndogermanisch: Verwandt mit tocharisch A \u003ci\u003ekoc,\u003c/i\u003e tocharisch B \u003ci\u003ekauc\u003c/i\u003e „hoch, nach oben“, altgriechisch \u003ci\u003eκύριος\u003c/i\u003e „Herrscher, Besitzer“, altindisch \u003ci\u003eśávīra\u003c/i\u003e „stark, mächtig“, kymrisch \u003ci\u003ecawr\u003c/i\u003e „Riese“. Wurzel demnach \u003ci\u003e*k’ou-ko-\u003c/i\u003e mit hypothetischer Bedeutung „groß, stark“\u003c/dd\u003e\u003cdd\u003e[11] Lehnbedeutung nach englischem \u003ci\u003ehigh\u0026#160;\u003c/i\u003e ‚[g]reat, or greater than normal, in quantity, size, or intensity‘\u003c/dd\u003e\u003c/dl\u003e"},{"header":{"de":"Synonyme","en":"synonyms"},"subentry":"\u003cdl\u003e\u003cdd\u003e[2] angestaut, angestiegen, emporragend, groß, haushoch, hochgewachsen, ragend\u003c/dd\u003e\u003cdd\u003e[4] angesehen, bedeutend, fein, führend, gehoben, hochgestellt, hochstehend, übergeordnet, vornehm\u003c/dd\u003e\u003cdd\u003e[6] groß, sehr, überteuert\u003c/dd\u003e\u003cdd\u003e[7] groß, maßlos, sehr, stattlich, viel\u003c/dd\u003e\u003cdd\u003e[8] lang, lebenslänglich\u003c/dd\u003e\u003cdd\u003e[11] heftig, kräftig, stark\u003c/dd\u003e\u003c/dl\u003e"},{"header":{"de":"Gegenwörter","en":"antonyms"},"subentry":"\u003cdl\u003e\u003cdd\u003e[1,\u0026#160;3] tief\u003c/dd\u003e\u003cdd\u003e[1, 2, 4] niedrig\u003c/dd\u003e\u003cdd\u003e[2] klein\u003c/dd\u003e\u003cdd\u003e[4] nieder\u003c/dd\u003e\u003c/dl\u003e"},{"header":{"de":"Unterbegriffe","en":"minor terms"},"subentry":"\u003cdl\u003e\u003cdd\u003e[2] kniehoch, haushoch, hüfthoch, mannshoch, Dreikäsehoch\u003c/dd\u003e\u003cdd\u003e[4] ranghoch\u003c/dd\u003e\u003c/dl\u003e"},{"header":{"de":"Beispiele","en":"examples"},"subentry":"\u003cdl\u003e\u003cdd\u003e[1] Die Hütte liegt \u003ci\u003ehoch\u003c/i\u003e in den Bergen.\u003c/dd\u003e\u003cdd\u003e[1] Das ist aber ganz schön \u003ci\u003ehoch\u003c/i\u003e hier.\u003c/dd\u003e\u003cdd\u003e[1] Die Schwalben fliegen heute wieder \u003ci\u003ehoch.\u003c/i\u003e\u003c/dd\u003e\u003cdd\u003e[2] Das Gebäude ist ziemlich \u003ci\u003ehoch.\u003c/i\u003e\u003c/dd\u003e\u003cdd\u003e[2] Die Schuhe haben \u003ci\u003ehohe\u003c/i\u003e Absätze.\u003c/dd\u003e\u003cdd\u003e[2] „Auch wenn die Schätzungen zu Hebungen in Afrika sehr weit auseinandergehen, gibt es doch Hinweise darauf, dass zum Beispiel das Gebirgsgebiet Namibias, welches aktuell bis über 2000 Meter \u003ci\u003ehoch\u003c/i\u003e aufragt, in den letzten 10 Millionen Jahren um etwa 1000 Meter angehoben wurde.“\u003c/dd\u003e\u003cdd\u003e[3] Heute spiele ich nur \u003ci\u003ehohe\u003c/i\u003e Töne.\u003c/dd\u003e\u003cdd\u003e[3] Frauen haben eine \u003ci\u003ehöhere\u003c/i\u003e Stimme als Männer.\u003c/dd\u003e\u003cdd\u003e[4] Möchten die \u003ci\u003ehohen\u003c/i\u003e Herrschaften noch etwas?\u003c/dd\u003e\u003cdd\u003e[4] Beim Militär gibt es niedere und \u003ci\u003ehöhere\u003c/i\u003e Dienstgrade.\u003c/dd\u003e\u003cdd\u003e[5] Fünf \u003ci\u003ehoch\u003c/i\u003e drei (5³) ist gleich einhundertfünfundzwanzig.\u003c/dd\u003e\u003cdd\u003e[6] Nach dem Hausbau hatte er \u003ci\u003ehohe\u003c/i\u003e Schulden.\u003c/dd\u003e\u003cdd\u003e[6] In der Innenstadt zahlt man eine \u003ci\u003ehohe\u003c/i\u003e Miete.\u003c/dd\u003e\u003cdd\u003e[6] Im Sommer haben wir immer \u003ci\u003ehohe\u003c/i\u003e Temperaturen.\u003c/dd\u003e\u003cdd\u003e[6] Die Zahl der Geflüchteten, die mit einem Schulabschluss nach Deutschland kommen, ist \u003ci\u003ehöher\u003c/i\u003e als oft angenommen wird.\u003c/dd\u003e\u003cdd\u003e[7] Sie stellte an ihre Mitarbeiter \u003ci\u003ehohe\u003c/i\u003e Ansprüche.\u003c/dd\u003e\u003cdd\u003e[7] Dafür übernahm sie aber auch ein \u003ci\u003ehohes\u003c/i\u003e Maß an Verantwortung.\u003c/dd\u003e\u003cdd\u003e[8] Schildkröten erreichen ein \u003ci\u003ehohes\u003c/i\u003e Alter.\u003c/dd\u003e\u003cdd\u003e[8] Es wird \u003ci\u003ehöchste\u003c/i\u003e Zeit, dass wir los gehen.\u003c/dd\u003e\u003cdd\u003e[9] Er will \u003ci\u003ehoch\u003c/i\u003e hinaus.\u003c/dd\u003e\u003cdd\u003e[9] DIN A6 nimmt man meistens quer, A4 meistens \u003ci\u003ehoch\u003c/i\u003e, A5 kann man \u003ci\u003ehoch\u003c/i\u003e oder quer beschriften.\u003c/dd\u003e\u003cdd\u003e[10] Das ist mir alles zu \u003ci\u003ehoch.\u003c/i\u003e\u003c/dd\u003e\u003cdd\u003e[11] „Im Nordwesten des Landes erwarten Meterologen sogar überdurchschnittlich \u003ci\u003ehohe\u003c/i\u003e Niederschläge.“\u003c/dd\u003e\u003cdd\u003e[11] „In Usakos regnete es gestern Nachmittag 11,0 mm, und in der Umgebung soll es zu \u003ci\u003ehöheren\u003c/i\u003e Niederschlägen gekommen sein.“\u003c/dd\u003e\u003cdd\u003e[11] „Am Dienstag wurden in Okaukuejo 15,4 mm gemessen, eine der \u003ci\u003ehöchsten\u003c/i\u003e Niederschläge in der bisherigen Regensaison, sagte ein Naturschutzbeamter.“\u003c/dd\u003e\u003cdd\u003e[11] „Durch die erwarteten \u003ci\u003ehohen\u003c/i\u003e Regenfälle im Auffanggebiet des Sambesiflusses in den westlichen Teilen Sambias und in Angola wird erwartet, dass der Stand des Flusses noch sehr stark ansteigen wird und möglicherweise große Teile der Flutflächen in der Caprivi-Region gefüllt werden.“\u003c/dd\u003e\u003cdd\u003e[11] „Für etliche Wochen konnte der Eigentümer der Wabi-Lodge nicht in viele Gebiete seiner Farm fahren, da das Gelände durch die anormal \u003ci\u003ehohen\u003c/i\u003e Regenfälle aufgeweicht war und Fahrzeuge sofort stecken geblieben wären.“\u003c/dd\u003e\u003cdd\u003e[11] „Dank der \u003ci\u003ehohen\u003c/i\u003e Regenfälle ist der Pegel des Kuiseb-Riviers auf der Farm Schlesien binnen 24 Stunden von 0,12 m auf 1,10 m gestiegen.“\u003c/dd\u003e\u003cdd\u003e[11] „Sehr \u003ci\u003ehohe\u003c/i\u003e Niederschläge wurden im Süden des Landes verzeichnet und das Wetteramt gab für Keetmanshoop fast 60 mm und für Karasburg und Koës über 40 mm bekannt.“\u003c/dd\u003e\u003cdd\u003e[11] „Trotz der zahlreichen \u003ci\u003ehohen\u003c/i\u003e Niederschläge in weiten Landesteilen gab es wenig Zulauf in die Dämme, die Windhoek mit Wasser versorgen.“\u003c/dd\u003e\u003c/dl\u003e"},{"header":{"de":"Redewendungen","en":"idioms"},"subentry":"\u003cdl\u003e\u003cdd\u003e[2] die \u003ci\u003ehohe\u003c/i\u003e See\u003c/dd\u003e\u003cdd\u003e[2] die Latte \u003ci\u003ehöher\u003c/i\u003e legen\u003c/dd\u003e\u003cdd\u003e[2] \u003ci\u003ehohe\u003c/i\u003e Wellen schlagen\u003c/dd\u003e\u003cdd\u003e[2] jemanden vom \u003ci\u003ehohen\u003c/i\u003e Ross stoßen\u003c/dd\u003e\u003cdd\u003e[2] auf die \u003ci\u003ehohe\u003c/i\u003e Kante legen\u003c/dd\u003e\u003cdd\u003e[3] in den \u003ci\u003ehöchsten\u003c/i\u003e Tönen loben\u003c/dd\u003e\u003cdd\u003e[4] \u003ci\u003ehohes\u003c/i\u003e Haus\u003c/dd\u003e\u003cdd\u003e[7] das \u003ci\u003ehöchste\u003c/i\u003e der Gefühle\u003c/dd\u003e\u003cdd\u003e[8] es ist \u003ci\u003ehöchste\u003c/i\u003e Eisenbahn\u003c/dd\u003e\u003cdd\u003e[8] es ist \u003ci\u003ehöchste\u003c/i\u003e Zeit\u003c/dd\u003e\u003cdd\u003e[9] Kopf \u003ci\u003ehoch\u003c/i\u003e!\u003c/dd\u003e\u003c/dl\u003e"},{"header":{"de":"Charakteristische Wortkombinationen","en":"characteristic word combinations"},"subentry":"\u003cdl\u003e\u003cdd\u003e[2] \u003ci\u003ehöchster\u003c/i\u003e Berg/Gipfel/Punkt, \u003ci\u003ehöchste\u003c/i\u003e Erhebung/Stelle, \u003ci\u003ehohe\u003c/i\u003e Stelle, \u003ci\u003ehoher\u003c/i\u003e Berg\u003c/dd\u003e\u003cdd\u003e[4] \u003ci\u003ehöhere\u003c/i\u003e Gewalt, \u003ci\u003ehohes\u003c/i\u003e Tier; \u003ci\u003eHoher\u003c/i\u003e Dom, \u003ci\u003eHohes\u003c/i\u003e Gericht, \u003ci\u003ehöchster\u003c/i\u003e Beamter/Dienstgrad/Herrscher/Rang/Würdenträger, \u003ci\u003ehoher\u003c/i\u003e Beamter/Dienstgrad/Rang\u003c/dd\u003e\u003cdd\u003e[5] \u003ci\u003ehoch\u003c/i\u003e zehn\u003c/dd\u003e\u003cdd\u003e[6] \u003ci\u003ehöchste\u003c/i\u003e Aggressivität/Brisanz/Dichte/Empfindlichkeit/Energie/Erregung/Genauigkeit/Geschwindigkeit/Intensität/Komplexität/Leistung/Präzision/Qualität/Stabilität/Verdichtung/Windgeschwindigkeit, \u003ci\u003ehöchster\u003c/i\u003e Ertrag, \u003ci\u003ehohe\u003c/i\u003e Aggressivität/Biodiversität/Brisanz/Dichte/Empfindlichkeit/Energie/Erregung/Genauigkeit/Geschwindigkeit/Intensität/Komplexität/Leistung/Luftfeuchtigkeit/Präzision/Qualität/Stabilität/Verdichtung/Windgeschwindigkeit, hoher Ertrag\u003c/dd\u003e\u003cdd\u003e[7] der \u003ci\u003ehöchste\u003c/i\u003e Anteil, die \u003ci\u003ehöchste\u003c/i\u003e Auflösung, die \u003ci\u003ehöchste\u003c/i\u003e Beanspruchung, die \u003ci\u003ehöchste\u003c/i\u003e Bedeutung, die \u003ci\u003ehöchste\u003c/i\u003e Effizienz, der \u003ci\u003ehöchste\u003c/i\u003e Grad an …, in \u003ci\u003ehöchster\u003c/i\u003e Not, die \u003ci\u003ehöchste\u003c/i\u003e Ordnung, in \u003ci\u003ehöchster\u003c/i\u003e Reinheit, die \u003ci\u003ehöchste\u003c/i\u003e Spezifität, in \u003ci\u003ehöchster\u003c/i\u003e Vollkommenheit, mit \u003ci\u003ehöchster\u003c/i\u003e Wahrscheinlichkeit, der \u003ci\u003ehöchste\u003c/i\u003e Wasserstand, der \u003ci\u003ehöchste\u003c/i\u003e Wert, die \u003ci\u003ehöchste\u003c/i\u003e Wichtigkeit haben\u003c/dd\u003e\u003cdd\u003e[7] eine \u003ci\u003ehohe\u003c/i\u003e Akzeptanz haben (\u003cspan class=audio-available audio=https://upload.wikimedia.org/wikipedia/commons/0/08/De-eine_hohe_Akzeptanz_haben.ogg\u003eAudio\u003c/span\u003e), eine \u003ci\u003ehohe\u003c/i\u003e Auflösung haben, eine \u003ci\u003ehohe\u003c/i\u003e Bedeutung haben, eine \u003ci\u003ehohe\u003c/i\u003e Meinung von jemandem haben, eine \u003ci\u003ehohe\u003c/i\u003e Ordnung haben, eine \u003ci\u003ehohe\u003c/i\u003e Spezifität haben, eine \u003ci\u003ehohe\u003c/i\u003e Wahrscheinlichkeit haben, eine \u003ci\u003ehohe\u003c/i\u003e Wichtigkeit haben\u003c/dd\u003e\u003cdd\u003e[7] ein \u003ci\u003ehoher\u003c/i\u003e Anteil, ein \u003ci\u003ehoher\u003c/i\u003e Wasserstand ein \u003ci\u003ehoher\u003c/i\u003e Wert\u003c/dd\u003e\u003cdd\u003e[?] \u003ci\u003ehoch\u003c/i\u003e im Norden (Gegensatz: tief im Süden)\u003c/dd\u003e\u003cdd\u003e[11] \u003ci\u003ehohe\u003c/i\u003e Niederschläge, Regenfälle\u003c/dd\u003e\u003c/dl\u003e"},{"header":{"de":"Wortbildungen","en":"word formations"},"subentry":"\u003cdl\u003e\u003cdd\u003e\u003ci\u003eWortbildungen mit dem Präfix für Adjektive und Verben „hoch-“ siehe:\u003c/i\u003e Verzeichnis:Deutsch/Wortbildungen/hoch-\u003c/dd\u003e\u003cdd\u003eaufhöhen, erhöhen, haushoch, himmelhoch, das Hoch, Hochachtung, Hochadel, Hochalemannisch, hochalemannisch, Hochaltar, Hochamt, Hochbahn, Hochbau, Hochbeet, Hochbetrieb, Hochbett, Hochblüte, Hochburg, hochdeutsch, Hochdeutsch, Hochdruck, Hochdruckgebiet, Hochebene, Hochehrwürden, Hochenergiephysik, Hochfest, Hochfinanz, Hochfläche, Hochflut, Hochformat, Hochfrequenz, Hochgebirge, Hochgefühl, Hochgenuss, Hochgericht, Hochglanz, Hochhaus, Hochjagd, hochkant, hochkantig, Hochkirche, Hochkommissar, Hochkonjunktur, Hochkultur, Hochland, Hochländer, hochländisch, Hochlautung, hochleben, Hochleistung, Hochleitung, hochliegen, Hochmeister, Hochmoor, Hochmut, hochmütig, hochnäsig, Hochnäsigkeit, Hochofen, Hochplateau, Hochprozentiges, Hochrechnung, Hochrelief, Hochruf, Hochsaison, Hochschätzung, Hochschule, Hochschüler, Hochsee, Hochseil, Hochsinn, hochsinnig, Hochsitz, Hochsommer, Hochspannung, Hochsprache, hochsprachlich, Hochsprung, Hochstand, hochstapeln, Hochstapelei, Hochstapler, Höchstbelastung, Höchstbietende, hochstehen, höchsteigen, Höchstgeschwindigkeit, Höchstgewicht, Hochstift, Hochstimmung, Höchstkurs, Höchstleistung, Höchstmaß, höchstpersönlich, Höchstpreis, Höchstpunktzahl, Hochstraße, Höchstsatz, Höchststrafe, Höchststufe, höchstwahrscheinlich, Höchstwert, höchstzulässig, Hochtal, Hochtempel, Hochtemperaturreaktor, Hochton, hochtönen, hochtonig, Hochtour, hochtourig, Hochtourist, Hochtouristik, hochtraben, Hochverrat, Hochverräter, hochverräterisch, hochverzinslich, Hochwald, Hochwasser, hochwertig, Hochwertigkeit, Hochwild, Hochwürden, Hochzahl, Hochzeit, Hochzeiter, Hochzeiterin, hochzeitlich, hoch zivilisiert, Hochzucht, hochzüchten, Hoffart, Höhe, Hoheit, kilometerhoch, meterhoch, turmhoch, Zwischenhoch\u003c/dd\u003e\u003c/dl\u003e"},{"header":{"de":"Übersetzungen","en":"translations"},"subentry":"\u0026#160;\u003ctable class=transtable\u003e\u003ctbody\u003e\u003ctr\u003e\u003ctd\u003e\u003cul\u003e\u003cli\u003eBulgarisch: [1,\u0026#160;2] висок\u0026#160;(visok)\u0026#160;\u003c/li\u003e\u003cli\u003eChinesisch: [1,\u0026#160;2] 高\u0026#160;(gāo)\u0026#160;\u003c/li\u003e\u003cli\u003eDänisch: [1] høj\u0026#160;\u003c/li\u003e\u003cli\u003eEnglisch: [1–4] high, tall\u0026#160;(ein Mensch oder ein Gebäude ist \u003ci\u003etall,\u003c/i\u003e aber ein Berg ist \u003ci\u003ehigh\u003c/i\u003e); [5] to the power of, to the; [11] high\u0026#160;\u003c/li\u003e\u003cli\u003eEsperanto: [2] alta\u0026#160;\u003c/li\u003e\u003cli\u003eFäröisch: [1] høgur\u0026#160;\u003c/li\u003e\u003cli\u003eFinnisch: [1–3] korkea\u0026#160;\u003c/li\u003e\u003cli\u003eFranzösisch: [1–4] haut; [5] puissance; [8] grand; [11] fort\u0026#160;\u003cem title=\"Genus: Maskulinum (grammatikalisches Geschlecht: männlich)\"\u003em\u003c/em\u003e / forte\u0026#160;\u003cem title=\"Genus: Femininum (grammatikal. Geschlecht: weiblich)\"\u003ef\u003c/em\u003e\u003c/li\u003e\u003cli\u003eGriechisch (Neu-): [1–3] ψηλός\u0026#160;(psilós)\u0026#160;\u003c/li\u003e\u003cli\u003eGrönländisch: [1] kingippoq, portuvoq\u0026#160;\u003c/li\u003e\u003cli\u003eInterlingua: [1–4, 6, 7] alte\u0026#160;\u003c/li\u003e\u003cli\u003eIsländisch: [1] hár\u0026#160;\u003c/li\u003e\u003cli\u003eItalienisch: [1] alto\u0026#160;\u003c/li\u003e\u003cli\u003eJapanisch: [1,\u0026#160;2] 高い\u0026#160;(たかい, takai)\u0026#160;\u003c/li\u003e\u003cli\u003eLatein: [1–4] altus\u0026#160;\u003c/li\u003e\u003c/ul\u003e\u003c/td\u003e\u003ctd\u003e\u003c/td\u003e\u003ctd\u003e\u003cul\u003e\u003cli\u003eLitauisch: [1,\u0026#160;2] aukštas\u0026#160;\u003c/li\u003e\u003cli\u003eNiederländisch: [1–8] hoog; [9] omhoog\u0026#160;\u003c/li\u003e\u003cli\u003eNorwegisch: [1] høg\u0026#160;\u003c/li\u003e\u003cli\u003ePolnisch: [1–3] wysoki\u0026#160;\u003c/li\u003e\u003cli\u003ePortugiesisch: [1–4] alto\u0026#160;\u003c/li\u003e\u003cli\u003eRumänisch: [1–3] înalt\u0026#160;\u003cem title=\"Genus: Maskulinum (grammatikalisches Geschlecht: männlich)\"\u003em\u003c/em\u003e, înaltă\u0026#160;\u003cem title=\"Genus: Femininum (grammatikal. Geschlecht: weiblich)\"\u003ef\u003c/em\u003e\u003c/li\u003e\u003cli\u003eRussisch: [1–3] высокий\u0026#160;(vysokij); [4] знатный\u0026#160;(znatnyj); [5] в степени; [6,\u0026#160;7] высокий, большой; [10] сложный\u0026#160;\u003c/li\u003e\u003cli\u003eSchwedisch: [1–4] hög; [5] upphöjt med; [6–9] hög; [10] svår\u0026#160;\u003c/li\u003e\u003cli\u003eSerbisch: [1 ] висок\u0026#160;(visok)\u0026#160;\u003c/li\u003e\u003cli\u003eSlowakisch: [1] vysoko; [2–4, 6–8] vysoký; [5] na; [10] priveľa\u0026#160;\u003c/li\u003e\u003cli\u003eSpanisch: [1–4] alto; [5] elevado a\u0026#160;\u003c/li\u003e\u003cli\u003eTschechisch: [1] vysoko; [2–4, 6–8] vysoký; [5] na; [10] příliš\u0026#160;\u003c/li\u003e\u003cli\u003eUkrainisch: [1, 2, 4, 6, 8] високий\u0026#160;()\u0026#160;\u003c/li\u003e\u003cli\u003eUngarisch: [1,\u0026#160;2] magas\u0026#160;\u003c/li\u003e\u003c/ul\u003e\u003c/td\u003e\u003c/tr\u003e\u003c/tbody\u003e\u003c/table\u003e\u003cp\u003e\u003ci\u003eQuellen:\u003c/i\u003e\u003cbr\u003e\u003c/p\u003e\u003col class=references\u003e\u003cli id=cite_note-1\u003e\u003cb\u003e↑\u003c/b\u003e Friedrich Kluge, bearbeitet von Elmar Seebold:\u0026#32;\u003ci\u003eEtymologisches Wörterbuch der deutschen Sprache.\u003c/i\u003e\u0026#32;24., durchgesehene und erweiterte\u0026#160;Auflage.\u0026#32;Walter de Gruyter,\u0026#32;Berlin/New York\u0026#32;2001,\u0026#32;ISBN 978-3-11-017473-1,\u0026#32;DNB 965096742, Stichwort: „hoch“, Seite 416.\u003c/li\u003e\u003cli id=cite_note-2\u003e\u003cb\u003e↑\u003c/b\u003e Oxford English Dictionary „high“\u003cbr\u003eVergleiche auch die Beispiele unter Bedeutung [1.1] in Oxford English Dictionary „rainfall“\u003c/li\u003e\u003cli id=cite_note-3\u003e\u003cb\u003e↑\u003c/b\u003e marum.de:\u0026#32;\u003ci\u003eWie Gebirge Meeresströmungen beeinflussen.\u003c/i\u003e\u0026#32;Abgerufen\u0026#32;am\u0026#32;26.\u0026#160;Januar\u0026#32;2016.\u003c/li\u003e\u003cli id=cite_note-4\u003e\u003cb\u003e↑\u003c/b\u003e \u003ci\u003eDeutschlehrer-Info - Zwei von drei Geflüchteten haben einen Schulabschluss.\u003c/i\u003e\u0026#32;In:\u0026#32;\u003ci\u003eDeutsche Welle.\u003c/i\u003e\u0026#32;\u0026#32;31.\u0026#160;August\u0026#32;2017\u0026#32;(URL,\u0026#32;abgerufen\u0026#32;am\u0026#32;31.\u0026#160;Januar\u0026#32;2018).\u003c/li\u003e\u003cli id=cite_note-5\u003e\u003cb\u003e↑\u003c/b\u003e \u003ci\u003eKein Grund zur \"Panik\".\u003c/i\u003e\u0026#32;In:\u0026#32;\u003ci\u003eAllgemeine Zeitung Online \u003c/i\u003e(Windhoek, Namibia)\u003ci\u003e.\u003c/i\u003e\u0026#32;\u0026#32;11.\u0026#160;Januar\u0026#32;2002,\u0026#32;ISSN 1560-9421\u0026#32;(URL,\u0026#32;abgerufen\u0026#32;am\u0026#32;17.\u0026#160;Juni\u0026#32;2018).\u003c/li\u003e\u003cli id=cite_note-6\u003e\u003cb\u003e↑\u003c/b\u003e \u003ci\u003eGute Niederschläge in Zentral-Namibia.\u003c/i\u003e\u0026#32;In:\u0026#32;\u003ci\u003eAllgemeine Zeitung Online \u003c/i\u003e(Windhoek, Namibia)\u003ci\u003e.\u003c/i\u003e\u0026#32;\u0026#32;6.\u0026#160;Januar\u0026#32;2004,\u0026#32;ISSN 1560-9421\u0026#32;(URL,\u0026#32;abgerufen\u0026#32;am\u0026#32;17.\u0026#160;Juni\u0026#32;2018).\u003c/li\u003e\u003cli id=cite_note-7\u003e\u003cb\u003e↑\u003c/b\u003e \u003ci\u003eKaum Wasser in Etoscha Pfanne.\u003c/i\u003e\u0026#32;In:\u0026#32;\u003ci\u003eAllgemeine Zeitung Online \u003c/i\u003e(Windhoek, Namibia)\u003ci\u003e.\u003c/i\u003e\u0026#32;\u0026#32;20.\u0026#160;Januar\u0026#32;2005,\u0026#32;ISSN 1560-9421\u0026#32;(URL,\u0026#32;abgerufen\u0026#32;am\u0026#32;17.\u0026#160;Juni\u0026#32;2018).\u003c/li\u003e\u003cli id=cite_note-8\u003e\u003cb\u003e↑\u003c/b\u003e \u003ci\u003eSchwache Aussicht.\u003c/i\u003e\u0026#32;In:\u0026#32;\u003ci\u003eAllgemeine Zeitung Online \u003c/i\u003e(Windhoek, Namibia)\u003ci\u003e.\u003c/i\u003e\u0026#32;\u0026#32;2.\u0026#160;März\u0026#32;2005,\u0026#32;ISSN 1560-9421\u0026#32;(URL,\u0026#32;abgerufen\u0026#32;am\u0026#32;17.\u0026#160;Juni\u0026#32;2018).\u003c/li\u003e\u003cli id=cite_note-9\u003e\u003cb\u003e↑\u003c/b\u003e \u003ci\u003eJunger Weißer Nashornbulle gewildert.\u003c/i\u003e\u0026#32;In:\u0026#32;\u003ci\u003eAllgemeine Zeitung Online \u003c/i\u003e(Windhoek, Namibia)\u003ci\u003e.\u003c/i\u003e\u0026#32;\u0026#32;8.\u0026#160;Juni\u0026#32;2011,\u0026#32;ISSN 1560-9421\u0026#32;(URL,\u0026#32;abgerufen\u0026#32;am\u0026#32;17.\u0026#160;Juni\u0026#32;2018).\u003c/li\u003e\u003cli id=cite_note-10\u003e\u003cb\u003e↑\u003c/b\u003e \u003ci\u003eHimmel öffnet seine Schleusen.\u003c/i\u003e\u0026#32;In:\u0026#32;\u003ci\u003eAllgemeine Zeitung Online \u003c/i\u003e(Windhoek, Namibia)\u003ci\u003e.\u003c/i\u003e\u0026#32;\u0026#32;28.\u0026#160;März\u0026#32;2012,\u0026#32;ISSN 1560-9421\u0026#32;(URL,\u0026#32;abgerufen\u0026#32;am\u0026#32;17.\u0026#160;Juni\u0026#32;2018).\u003c/li\u003e\u003cli id=cite_note-11\u003e\u003cb\u003e↑\u003c/b\u003e Dirk Heinrich:\u0026#32;\u003ci\u003eHeftige Regenfälle im Süden des Landes.\u003c/i\u003e\u0026#32;In:\u0026#32;\u003ci\u003eAllgemeine Zeitung Online \u003c/i\u003e(Windhoek, Namibia)\u003ci\u003e.\u003c/i\u003e\u0026#32;\u0026#32;20.\u0026#160;Januar\u0026#32;2016,\u0026#32;ISSN 1560-9421\u0026#32;(URL,\u0026#32;abgerufen\u0026#32;am\u0026#32;17.\u0026#160;Juni\u0026#32;2018).\u003c/li\u003e\u003cli id=cite_note-12\u003e\u003cb\u003e↑\u003c/b\u003e Dirk Heinrich:\u0026#32;\u003ci\u003eNaute steigert um 19 Prozent.\u003c/i\u003e\u0026#32;Omatako nur zu 1,5 Prozent voll – 185 mm in 50 Stunden – Von-Bach wenig Zufluss.\u0026#32;In:\u0026#32;\u003ci\u003eAllgemeine Zeitung.\u003c/i\u003e\u0026#32;\u0026#32;Aktuell Mittendrin Für Dich.\u0026#32;Nummer\u0026#32;15,\u0026#32;22.\u0026#160;Januar\u0026#32;2016,\u0026#32;ISSN 1560-9421,\u0026#32;Seite\u0026#160;1.\u003c/li\u003e\u003c/ol\u003e"}],"tables":[{"Komparativ":"höher","Positiv":"hoch","Superlativ":"höchsten","html":"\u003ctable class=wikitable\u003e\u003ctbody\u003e\u003ctr\u003e\u003cth\u003e\u003cspan lang=de\u003ePositiv\u003c/span\u003e\u003cbr\u003e\u003cspan lang=en class=trans\u003epositive\u003c/span\u003e\u003c/th\u003e\u003cth\u003e\u003cspan lang=de\u003eKomparativ\u003c/span\u003e\u003cbr\u003e\u003cspan lang=en class=trans\u003ecomparative\u003c/span\u003e\u003c/th\u003e\u003cth\u003e\u003cspan lang=de\u003eSuperlativ\u003c/span\u003e\u003cbr\u003e\u003cspan lang=en class=trans\u003esuperlative\u003c/span\u003e\u003c/th\u003e\u003c/tr\u003e\u003ctr align=center\u003e\u003ctd\u003ehoch\u003c/td\u003e\u003ctd\u003ehöher\u003c/td\u003e\u003ctd\u003eam\u0026#32;höchsten\u003c/td\u003e\u003c/tr\u003e\u003ctr\u003e\u003cth style=font-weight:400 colspan=5\u003e\u003cspan lang=de\u003e\u003ci\u003eAlle weiteren Formen:\u003c/i\u003e \u003ca href=https://de.wiktionary.org/wiki/Flexion:hoch target=_blank\u003eFlexion:hoch\u003c/a\u003e\u003c/span\u003e\u003cbr\u003e\u003cspan lang=en class=trans\u003e\u003ci\u003eAll other forms:\u003c/i\u003e \u003ca href=https://de.wiktionary.org/wiki/Flexion:hoch target=_blank\u003eFlexion:hoch\u003c/a\u003e\u003c/span\u003e\u003c/th\u003e\u003c/tr\u003e\u003c/tbody\u003e\u003c/table\u003e"},{"html":"\u003ctable class=wikitable\u003e\u003ctbody\u003e\u003ctr\u003e\u003ctd colspan=10\u003e\u003cimg alt src=https://upload.wikimedia.org/wikipedia/commons/thumb/2/22/Cremona03.jpg/220px-Cremona03.jpg decoding=async width=220 height=293 class=thumbimage srcset=\"//upload.wikimedia.org/wikipedia/commons/thumb/2/22/Cremona03.jpg/330px-Cremona03.jpg 1.5x, //upload.wikimedia.org/wikipedia/commons/thumb/2/22/Cremona03.jpg/440px-Cremona03.jpg 2x\" data-file-width=768 data-file-height=1024\u003e\u003cp\u003e[2] ein \u003ci\u003ehoher\u003c/i\u003e Turm (Cremona, Torrazzo)\u003c/p\u003e\u003c/td\u003e\u003c/tr\u003e\u003c/tbody\u003e\u003c/table\u003e"}]},{"header":{"de":"Adverb","en":"adverb"},"subentries":[{"header":{"de":"Aussprache","en":"pronunciation"},"subentry":"\u003cdl\u003e\u003cdd\u003eIPA: [hoːx]\u003c/dd\u003e\u003cdd\u003eHörbeispiele: \u003cspan class=audio-available audio=https://upload.wikimedia.org/wikipedia/commons/8/84/De-hoch.ogg\u003ehoch\u003c/span\u003e\u003c/dd\u003e\u003c/dl\u003e"},{"header":{"de":"Bedeutungen","en":"meanings"},"subentry":"\u003cdl\u003e\u003cdd\u003e[1] sehr, äußerst\u003c/dd\u003e\u003c/dl\u003e"},{"header":{"de":"Herkunft","en":"origin"},"subentry":"\u003cdl\u003e\u003cdd\u003evom Adjektiv \u003ci\u003ehoch\u003c/i\u003e\u003c/dd\u003e\u003c/dl\u003e"},{"header":{"de":"Synonyme","en":"synonyms"},"subentry":"\u003cdl\u003e\u003cdd\u003e[1] sehr, äußerst\u003c/dd\u003e\u003c/dl\u003e"},{"header":{"de":"Sinnverwandte Wörter","en":"words with similar meanings"},"subentry":"\u003cdl\u003e\u003cdd\u003e[1] höchst\u003c/dd\u003e\u003c/dl\u003e"},{"header":{"de":"Beispiele","en":"examples"},"subentry":"\u003cdl\u003e\u003cdd\u003e[1] Er ist bei seinen Mitarbeitern \u003ci\u003ehoch\u003c/i\u003e angesehen.\u003c/dd\u003e\u003c/dl\u003e"},{"header":{"de":"Redewendungen","en":"idioms"},"subentry":"\u003cdl\u003e\u003cdd\u003e[1] wenn es hoch kommt - höchstens\u003c/dd\u003e\u003cdd\u003e[1] nach Höherem streben - versuchen, beruflich höher zu steigen; sein Leben stark an geistigen Idealen orientieren\u003c/dd\u003e\u003cdd\u003e[1] hoch hinaus wollen - versuchen nach etwas Höherem zu streben\u003c/dd\u003e\u003c/dl\u003e"},{"header":{"de":"Charakteristische Wortkombinationen","en":"characteristic word combinations"},"subentry":"\u003cdl\u003e\u003cdd\u003e[1] \u003ci\u003ehoch\u003c/i\u003e angesehen, \u003ci\u003ehoch\u003c/i\u003e empfindlich, \u003ci\u003ehoch\u003c/i\u003e erfreut, \u003ci\u003ehoch\u003c/i\u003e schätzen, \u003ci\u003ehöchst\u003c/i\u003e selten, \u003ci\u003ehoch\u003c/i\u003e verehren, \u003ci\u003ehoch\u003c/i\u003e gewachsen\u003c/dd\u003e\u003c/dl\u003e"},{"header":{"de":"Wortbildungen","en":"word formations"},"subentry":"\u003cdl\u003e\u003cdd\u003e\u003ci\u003esiehe ausschließlich:\u003c/i\u003e Verzeichnis:Deutsch/Wortbildungen/hoch-\u003c/dd\u003e\u003c/dl\u003e"},{"header":{"de":"Übersetzungen","en":"translations"},"subentry":"\u0026#160;\u003ctable class=transtable\u003e\u003ctbody\u003e\u003ctr\u003e\u003ctd\u003e\u003cul\u003e\u003cli\u003eEnglisch: [1] high, extremely\u0026#160;\u003c/li\u003e\u003cli\u003eFranzösisch: [1] très\u0026#160;\u003c/li\u003e\u003cli\u003eSardisch: [1] altamente\u003c/li\u003e\u003cli\u003eSchwedisch: [1] högt, mycket\u0026#160;\u003c/li\u003e\u003c/ul\u003e\u003c/td\u003e\u003ctd\u003e\u003c/td\u003e\u003ctd\u003e\u003cul\u003e\u003cli\u003eSpanisch: [1] muy\u0026#160;\u003c/li\u003e\u003cli\u003eTschechisch: [1] vysoce\u0026#160;\u003c/li\u003e\u003c/ul\u003e\u003c/td\u003e\u003c/tr\u003e\u003c/tbody\u003e\u003c/table\u003e"}],"tables":[{"Komparativ":"höher","Superlativ":"höchsten","html":"\u003ctable class=wikitable\u003e\u003ctbody\u003e\u003ctr\u003e\u003cth\u003e\u003cspan lang=de\u003ePositiv\u003c/span\u003e\u003cbr\u003e\u003cspan lang=en class=trans\u003epositive\u003c/span\u003e\u003c/th\u003e\u003cth\u003e\u003cspan lang=de\u003eKomparativ\u003c/span\u003e\u003cbr\u003e\u003cspan lang=en class=trans\u003ecomparative\u003c/span\u003e\u003c/th\u003e\u003cth\u003e\u003cspan lang=de\u003eSuperlativ\u003c/span\u003e\u003cbr\u003e\u003cspan lang=en class=trans\u003esuperlative\u003c/span\u003e\u003c/th\u003e\u003c/tr\u003e\u003ctr align=center\u003e\u003ctd\u003ehoch\u003c/td\u003e\u003ctd\u003ehöher\u003c/td\u003e\u003ctd\u003eam\u0026#32;höchsten\u003c/td\u003e\u003c/tr\u003e\u003c/tbody\u003e\u003c/table\u003e"}]}],"title":"hoch","translation":"high, extremely ","variants":["hoch","hoches","hochem","hochen","hoche","hocher","höher","höchsten"],"word classes":["Adjektiv","Adverb"]},"id":"hoch"}